MANIFEST.in
README.rst
requirements.txt
setup.py
itunes/__init__.py
itunes/base.py
itunes/search.py
pyitunes.egg-info/PKG-INFO
pyitunes.egg-info/SOURCES.txt
pyitunes.egg-info/dependency_links.txt
pyitunes.egg-info/not-zip-safe
pyitunes.egg-info/requires.txt
pyitunes.egg-info/top_level.txt