Metadata-Version: 1.0
Name: pyitunes
Version: 1.0.1
Summary: A simple python wrapper to access iTunes Store API
Home-page: https://github.com/moogar0880/python-itunes
Author: Jonathan Nappi
Author-email: moogar@comcast.net
License: http://www.gnu.org/copyleft/gpl.html
Platform: any
